gsc_light/__init__.py
gsc_light/gsc_client.py
gsc_light/oauth.py
gsc_light/parse_report.py
gsclight/__init__.py
gsclight/gsc_client.py
gsclight/oauth.py
gsclight/parse_report.py
gsclight-0.0.1.dist-info/LICENSE
gsclight-0.0.1.dist-info/METADATA
gsclight-0.0.1.dist-info/WHEEL
gsclight-0.0.1.dist-info/top_level.txt
gsclight-0.0.1.dist-info/RECORD
