Metadata-Version: 2.1
Name: gsclight
Version: 0.0.1
Summary: A simplified package for Google Search Console API
Home-page: https://github.com/GunnarGriese/google-search-console
Author: Gunnar Griese
Author-email: gugriese.gg@gmail.com
License: UNKNOWN
Platform: UNKNOWN
Classifier: Programming Language :: Python :: 3
Classifier: License :: OSI Approved :: MIT License
Classifier: Operating System :: OS Independent
Requires-Python: >=3.6
